astrora-0.1.1.dist-info/METADATA
astrora-0.1.1.dist-info/WHEEL
astrora/PYTHON_DOCSTRINGS_COMPLETE.md
astrora/__init__.py
astrora/_core.abi3.so
astrora/bodies.py
astrora/coordinates.py
astrora/maneuver.py
astrora/plotting/__init__.py
astrora/plotting/animation.py
astrora/plotting/groundtrack.py
astrora/plotting/interactive.py
astrora/plotting/porkchop.py
astrora/plotting/static.py
astrora/time.py
astrora/twobody/__init__.py
astrora/twobody/orbit.py
astrora/units.py
astrora/util.py
astrora-0.1.1.dist-info/RECORD
