Metadata-Version: 2.4
Name: astrora
Version: 0.1.1
Classifier: Development Status :: 3 - Alpha
Classifier: Intended Audience :: Science/Research
Classifier: Intended Audience :: Education
Classifier: License :: OSI Approved :: MIT License
Classifier: Operating System :: OS Independent
Classifier: Programming Language :: Python :: 3
Classifier: Programming Language :: Python :: 3.8
Classifier: Programming Language :: Python :: 3.9
Classifier: Programming Language :: Python :: 3.10
Classifier: Programming Language :: Python :: 3.11
Classifier: Programming Language :: Python :: 3.12
Classifier: Programming Language :: Python :: 3.13
Classifier: Programming Language :: Rust
Classifier: Topic :: Scientific/Engineering :: Astronomy
Classifier: Topic :: Scientific/Engineering :: Physics
Requires-Dist: numpy>=1.20
Requires-Dist: astropy>=5.0
Requires-Dist: scipy>=1.7
Requires-Dist: matplotlib>=3.5
Requires-Dist: plotly>=5.0
Requires-Dist: jplephem>=2.18
Requires-Dist: pytest>=7.0 ; extra == 'dev'
Requires-Dist: pytest-cov>=4.0 ; extra == 'dev'
Requires-Dist: pytest-xdist>=3.0 ; extra == 'dev'
Requires-Dist: pytest-benchmark>=4.0 ; extra == 'dev'
Requires-Dist: black>=23.0 ; extra == 'dev'
Requires-Dist: ruff>=0.1 ; extra == 'dev'
Requires-Dist: mypy>=1.0 ; extra == 'dev'
Requires-Dist: maturin>=1.0 ; extra == 'dev'
Requires-Dist: sphinx>=5.0 ; extra == 'docs'
Requires-Dist: sphinx-rtd-theme>=1.0 ; extra == 'docs'
Requires-Dist: sphinx-autodoc-typehints>=1.19 ; extra == 'docs'
Requires-Dist: numpydoc>=1.5 ; extra == 'docs'
Requires-Dist: pytest>=7.0 ; extra == 'test'
Requires-Dist: pytest-cov>=4.0 ; extra == 'test'
Requires-Dist: pytest-xdist>=3.0 ; extra == 'test'
Provides-Extra: dev
Provides-Extra: docs
Provides-Extra: test
Summary: Astrora - Rust-backed astrodynamics library for Python
Keywords: astrodynamics,orbital-mechanics,aerospace,space,orbit,kepler
Author-email: Cache McClure <cache.mcclure@gmail.com>
License: MIT
Requires-Python: >=3.8
Project-URL: Homepage, https://github.com/cachemcclure/astrora
Project-URL: Documentation, https://github.com/cachemcclure/astrora#readme
Project-URL: Repository, https://github.com/cachemcclure/astrora
Project-URL: Bug Tracker, https://github.com/cachemcclure/astrora/issues
